sample_EDAplayground/design3.sv
//*****************************************************************************
// File Name            : Modulo.v
// Project             : RSA Project
// Designer             : yasuhiro 
// History              : 2022/8/17
//_____________________________________________________________________________
// Description;
//                      Hreg = M mod C
//*****************************************************************************
`timescale 1ns/1ps

`define Init    0   //state
`define Sub     1   //state
`define Shift   2   //state
`define Bit     8   //#Bit modulo
`define Bit1    9   //Bit+1
`define Bit2    16  //Bit*2
`define BitN    3   //#Bit is BitN bit
`define BitN1   4   //BitN+1

module Modulo(clk, start, busy, C, Hreg, Lreg, M);

input clk, start;
input [`Bit-1:0] C;
input [`Bit:0] Hreg;
input [`Bit-1:0] Lreg;
output busy;
output [`Bit-1:0] M;

reg busy;
reg [`Bit:0] Hreg2;
reg [`Bit-1:0] Lreg2;
reg [1:0] state;
reg [`BitN:0] count;
wire [`Bit-1:0] M;
wire [`Bit:0] diff;

assign M = Hreg2[`Bit-1:0];  
assign diff = Hreg2 - C;

always @(posedge clk or negedge start) begin
if(!start) begin    //Ready
    busy <= 0;
    count <= `BitN1'd`Bit1;
    state <= 2'd`Init;
end else begin
    if(count != 0) begin
        if(state == `Init) begin    //Initialization state
            Hreg2 <= Hreg;
            Lreg2 <= Lreg;
            busy <= 1;
            state <= `Sub;
        end else if(state == `Sub) begin    //Substract state
            Hreg2 <= (diff[`Bit]? Hreg2 : diff[`Bit-1:0]);                      
          	count <= count - 1;
            state <= `Shift;
        end else if(state == `Shift) begin  //Shift state
            {Hreg2, Lreg2} <= {Hreg2[`Bit-1:0], Lreg2[`Bit-1:0], 1'b0};
            state <= `Sub;
        end else begin
            busy <= 0;  //illigal state
        end
    end else begin
    busy <= 0;  //Finish
    end
end
end

endmodule

$EDAplayground/design2.sv
//*****************************************************************************
// File Name            : Smulti.v
// Project             : RSA Project
// Designer             : yasuhiro 
// History              : 2022/8/17
//_____________________________________________________________________________
// Description;
//                      M <= A * B
//*****************************************************************************
`timescale 1ns/1ps

`define Init    0   //state
`define Add     1   //state
`define Shift   2   //state
`define Bit     8   //#Bit multiplier
`define Bit2    16  //Bit*2
`define BitN    3   //#Bit is BitN bit
`define BitN1   4   //BitN+1

module S_multi(clk, start, busy, A, B, Hreg, Lreg);

input clk, start;
input [`Bit-1:0] A,B;
output busy;
output [`Bit:0] Hreg;
output [`Bit-1:0] Lreg;

reg busy;
reg [`Bit:0] Hreg;
reg [`Bit-1:0] Lreg;
reg [1:0] state;
reg [`BitN:0] count;
wire [`Bit:0] sum;

assign sum = Hreg + A;

always @(posedge clk or negedge start) begin
if(!start) begin    //Ready
    busy <= 0;
    count <= `BitN1'd`Bit;
    state <= 2'd`Init;
end else begin
    if(count != 0) begin
        if(state == `Init) begin    //Initialization
            Hreg <= 0;
            Lreg <= B;
            busy <= 1;
            state <= `Add;
        end else if(state == `Add) begin  //Check Lreg's LSB
            Hreg <= (Lreg[0] ? sum : Hreg);
            state <= `Shift;
        end else if(state == `Shift) begin   //Shifter
            {Hreg, Lreg} <= {1'b0, Hreg, Lreg[`Bit-1:1]};
            count <= count - 1;
            state <= `Add;
        end else begin
            busy <= 0;  //illigal state
        end
    end else begin
    busy <= 0;  //Finish
    end
end
end

endmodule

EDAplayground/design.sv
//*****************************************************************************
// File Name            : RSA.v
// Project             : RSA Project
// Designer             : yasuhiro 
// History              : 2022/8/17
//_____________________________________________________________________________
// Description;
//                      mod(A^B,C)
//*****************************************************************************
`include "design2.sv"
`include "design3.sv"

`timescale 1ns/1ps

`define Init                0   //state
`define XnORXnYn            1   //state
`define Xn_selectXn         2   //state
`define Xn_startMul         3   //state
`define Xn_waitMul          4   //state
`define Xn_waitFlagMul      5   //state
`define Xn_startMod         6   //state
`define Xn_waitMod          7   //state
`define Xn_waitFlagMod      8   //state
`define Xn_saveXn           9   //state
`define XnYn_selectXn       10   //state
`define XnYn_startMul1      11   //state
`define XnYn_waitMul        12  //state
`define XnYn_waitFlagMul    13  //state
`define XnYn_startMod1      14  //state
`define XnYn_startMul2      15  //state
`define XnYn_waitMulMod     16  //state
`define XnYn_waitFlagMulMod 17  //state
`define XnYn_saveXn         18  //state
`define XnYn_startMod2      19  //state
`define XnYn_waitMod        20  //state
`define XnYn_waitFlagMod    21  //state
`define XnYn_saveYn         22  //state
`define FinalORnot          23  //state
`define Shift               24  //state
`define Final               25  //state
`define Bit                 8   //8bit multiplier
`define Bit1                7   //8bit multiplier

module RSA(clk, start, busy, A, B, C, Yn);

input clk, start;
input [`Bit-1:0] A,B,C;
output [`Bit-1:0] Yn;
output busy;

reg busy;
reg [`Bit-1:0] Xn, Yn ,Breg,Creg;
reg [4:0]state;
reg mux, mul_start,  mod_start;
wire mul_busy,mod_busy;
  wire [`Bit-1:0] mod_out, Lreg, mux_out;
wire [`Bit:0] Hreg;

S_multi     Mul(.clk(clk),.start(mul_start),.busy(mul_busy),.A(mux_out),.B(Xn),.Hreg(Hreg),.Lreg(Lreg));
Modulo      Mod(.clk(clk),.start(mod_start),.busy(mod_busy),.C(Creg),.Hreg(Hreg),.Lreg(Lreg),.M(mod_out));

assign      mux_out = mux? Xn:Yn;

always @(posedge clk or negedge start) begin
if(!start) begin    //Ready
    busy <= 0;
    mul_start <= 0;
    mod_start <= 0;
    state <= 5'd`Init;
end else begin
    if (state==`Init) begin    //initialization
        busy <= 1;
        Xn <= A;
        Yn <= `Bit1'h01;
        Breg <= B;
        Creg <= C;
        state <= `XnORXnYn;
    end else if (state==`XnORXnYn) begin
        state <= ((Breg[0]==0)? `Xn_selectXn : `XnYn_selectXn);
    end else if (state==`Xn_selectXn) begin
        mux <= 1;
        state <= `Xn_startMul;
    end else if (state==`Xn_startMul) begin
        mul_start <= 1;
        state <= `Xn_waitFlagMul;
    end else if (state==`Xn_waitFlagMul) begin
        state <= `Xn_waitMul;
    end else if (state==`Xn_waitMul) begin
        state <= ((mul_busy==1)? `Xn_waitMul:`Xn_startMod);
    end else if (state==`Xn_startMod) begin
        mul_start <= 0;
        mod_start <= 1;
        state <= `Xn_waitFlagMod;
    end else if (state==`Xn_waitFlagMod) begin
        state <= `Xn_waitMod;
    end else if (state==`Xn_waitMod) begin
        state <= ((mod_busy==1)? `Xn_waitMod:`Xn_saveXn);
    end else if (state==`Xn_saveXn) begin
        mod_start <= 0;
        Xn <= mod_out;
        state <= `Shift;
    end else if (state==`XnYn_selectXn) begin
        mux <= 1;
        state <= `XnYn_startMul1;
    end else if (state==`XnYn_startMul1) begin
        mul_start <= 1;
        state <= `XnYn_waitFlagMul;
    end else if (state==`XnYn_waitFlagMul) begin
        state <= `XnYn_waitMul;       
    end else if (state==`XnYn_waitMul) begin
        state <= ((mul_busy==1)? `XnYn_waitMul: `XnYn_startMod1);
    end else if (state==`XnYn_startMod1) begin
        mul_start <= 0;
        mod_start <= 1;
        mux <= 0;
        state <= `XnYn_startMul2;
    end else if (state==`XnYn_startMul2) begin
        mul_start <= 1;
        state <= `XnYn_waitFlagMulMod;
    end else if (state==`XnYn_waitFlagMulMod) begin
        state <= `XnYn_waitMulMod;
    end else if (state==`XnYn_waitMulMod) begin
        state <= (((mul_busy==1)||(mod_busy==1))? `XnYn_waitMulMod: `XnYn_saveXn);
    end else if (state==`XnYn_saveXn) begin
        mul_start <= 0;
        mod_start <= 0;
        Xn <= mod_out;
        state <= `XnYn_startMod2;
    end else if (state==`XnYn_startMod2) begin
        mod_start <= 1;
        state <= `XnYn_waitFlagMod;
    end else if (state==`XnYn_waitFlagMod) begin
        state <= `XnYn_waitMod;
    end else if (state==`XnYn_waitMod) begin
        state <= ((mod_busy==1)? `XnYn_waitMod: `XnYn_saveYn);       
    end else if (state==`XnYn_saveYn) begin   
        mod_start <= 0;
        Yn <= mod_out;
        state <= `Shift;        
    end else if (state==`Shift) begin
      Breg <= {1'b0, Breg[`Bit-1:1]};
        state <= `FinalORnot;
    end else if (state==`FinalORnot) begin     
      state <= ((Breg==0)? `Final:`XnORXnYn);
    end else if (state==`Final) begin
        busy <= 0;
    end else begin
        busy <= 0;      //illegal state
    end
end
end

endmodule

sample_EDAplayground/testbench.sv
//*****************************************************************************
// File Name            : RSA_Func_test.v
// Project             : RSA Project
// Designer             : yasuhiro 
// History              : 2022/8/20
//_____________________________________________________________________________
// Description;
//                      test mod(A^B,C)
//*****************************************************************************
`timescale 1ns/1ps


`define Bit     8   //8bit multiplier


`define delay   10

module RSA_test;

reg [`Bit*3-1:0] mem [0:9];
reg [`Bit-1:0] Expect;

reg clk, start;
reg [`Bit-1:0] A,B,C;
wire [`Bit-1:0] Yn;
wire busy;

integer i;

RSA RSA(clk, start, busy, A, B, C, Yn);

always #50  clk = ~clk;

initial begin
  $dumpfile("dump.vcd");
  $dumpvars;
  #700000 
  $finish;
end

function [`Bit-1:0] rsa;
    input [`Bit-1:0] A,B,C;
    integer j;
    reg [`Bit-1:0] Temp1, Temp2;
    reg [`Bit*2-1:0] Temp3;
begin
    Temp1 = A;
    Temp2 = 1;
    for (j=0; j<10; j=j+1) begin
        if(B[0]) begin
           Temp3 = Temp1 * Temp2;
           Temp2 = Temp3 % C; 
        end
        Temp3 = Temp1 * Temp1;
        Temp1 = Temp3 % C;
        B = {1'b0, B[`Bit-1:1]};
    end
    rsa = Temp2;
end  
endfunction

initial begin
  mem[0] = {`Bit'haf,`Bit'haf,`Bit'hff};
  mem[1] = {`Bit'h0e,`Bit'haf,`Bit'h0f};
  mem[2] = {`Bit'h0d,`Bit'hee,`Bit'h0f};
  mem[3] = {`Bit'hac,`Bit'hbb,`Bit'hef};
  mem[4] = {`Bit'h2b,`Bit'b00000101,`Bit'h3a};
  mem[5] = {`Bit'hfa,`Bit'b01110101,`Bit'haa};
  mem[6] = {`Bit'h99,`Bit'b01110101,`Bit'hba};
  mem[7] = {`Bit'h48,`Bit'b00000101,`Bit'haa};
  mem[8] = {`Bit'hf7,`Bit'b00000101,`Bit'ha1};
  mem[9] = {`Bit'h6a,`Bit'b00000101,`Bit'haa};
    clk=1;

    for(i=0;i<10;i=i+1)begin
        start = 0;
        {A,B,C} = mem[i];
        Expect = rsa(A,B,C);
        @(posedge clk)  #`delay;
        start = 1;
        @(posedge clk)  #`delay;

    while (busy==1) @(posedge clk);

    if(Expect==Yn) begin
        $display("Match Yn=%h Expect=%h",Yn,Expect);
    end else begin
        $display("Error Yn=%h Expect=%h",Yn,Expect);
    end
        
    end
$finish;
end

endmodule

sample_EDAplayground/dump.vcd
$date
	Sat Aug 27 02:43:29 2022
$end
$version
	Icarus Verilog
$end
$timescale
	1ps
$end
$scope module RSA_test $end
$var wire 8 ! Yn [7:0] $end
$var wire 1 " busy $end
$var reg 8 # A [7:0] $end
$var reg 8 $ B [7:0] $end
$var reg 8 % C [7:0] $end
$var reg 8 & Expect [7:0] $end
$var reg 1 ' clk $end
$var integer 32 ( i [31:0] $end
$var reg 1 ) start $end
$scope function rsa $end
$var reg 8 * A [7:0] $end
$var reg 8 + B [7:0] $end
$var reg 8 , C [7:0] $end
$var reg 8 - Temp1 [7:0] $end
$var reg 8 . Temp2 [7:0] $end
$var reg 16 / Temp3 [15:0] $end
$var integer 32 0 j [31:0] $end
$var reg 8 1 rsa [7:0] $end
$upscope $end
$scope module RSA $end
$var wire 8 2 A [7:0] $end
$var wire 8 3 B [7:0] $end
$var wire 8 4 C [7:0] $end
$var wire 9 5 Hreg [8:0] $end
$var wire 8 6 Lreg [7:0] $end
$var wire 1 7 clk $end
$var wire 1 8 mod_busy $end
$var wire 8 9 mod_out [7:0] $end
$var wire 1 : mul_busy $end
$var wire 8 ; mux_out [7:0] $end
$var wire 1 < start $end
$var reg 8 = Breg [7:0] $end
$var reg 8 > Creg [7:0] $end
$var reg 8 ? Xn [7:0] $end
$var reg 8 @ Yn [7:0] $end
$var reg 1 A busy $end
$var reg 1 B mod_start $end
$var reg 1 C mul_start $end
$var reg 1 D mux $end
$var reg 5 E state [4:0] $end
$scope module Mul $end
$var wire 8 F A [7:0] $end
$var wire 8 G B [7:0] $end
$var wire 1 7 clk $end
$var wire 1 H start $end
$var wire 9 I sum [8:0] $end
$var reg 9 J Hreg [8:0] $end
$var reg 8 K Lreg [7:0] $end
$var reg 1 L busy $end
$var reg 4 M count [3:0] $end
$var reg 2 N state [1:0] $end
$upscope $end
$scope module Mod $end
$var wire 8 O C [7:0] $end
$var wire 9 P Hreg [8:0] $end
$var wire 8 Q Lreg [7:0] $end
$var wire 8 R M [7:0] $end
$var wire 1 7 clk $end
$var wire 9 S diff [8:0] $end
$var wire 1 T start $end
$var reg 9 U Hreg2 [8:0] $end
$var reg 8 V Lreg2 [7:0] $end
$var reg 1 W busy $end
$var reg 4 X count [3:0] $end
$var reg 2 Y state [1:0] $end
$upscope $end
$upscope $end
$upscope $end
$enddefinitions $end
#0
$dumpvars
b0 Y
b1001 X
0W
bx V
bx U
0T
bx S
bx R
bx Q
bx P
bx O
b0 N
b1000 M
0L
bx K
bx J
bx I
0H
bx G
bx F
b0 E
xD
0C
0B
0A
bx @
bx ?
bx >
bx =
0<
bx ;
0:
bx 9
08
17
bx 6
bx 5
b11111111 4
b10101111 3
b10101111 2
b10100000 1
b1010 0
b1010010000101001 /
b10100000 .
b11001101 -
b11111111 ,
b0 +
b10101111 *
0)
b0 (
1'
b10100000 &
b11111111 %
b10101111 $
b10101111 #
0"
bx !
$end
#50000
0'
07
#100000
1'
17
#110000
1)
1<
#150000
0'
07
#200000
bx0x0xxx1 ;
bx0x0xxx1 F
b1 E
b11111111 >
b11111111 O
b10101111 =
b1 @
b1 !
b10101111 ?
b10101111 G
1A
1"
1'
17
#250000
0'
07
#300000
b1010 E
1'
17
#350000
0'
07
#400000
b10101111 ;
b10101111 F
b1011 E
1D
1'
17
#450000
0'
07
#500000
b1101 E
1C
1H
1'
17
#550000
0'
07
#600000
b1 N
1L
1:
b10101111 K
b10101111 6
b10101111 Q
b0 J
b10101111 I
b0 5
b0 P
b1100 E
1'
17
#650000
0'
07
#700000
b10 N
b10101111 J
b101011110 I
b10101111 5
b10101111 P
1'
17
#750000
0'
07
#800000
b1 N
b111 M
b1010111 J
b100000110 I
b1010111 5
b1010111 P
b11010111 K
b11010111 6
b11010111 Q
1'
17
#850000
0'
07
#900000
b10 N
b100000110 J
b110110101 I
b100000110 5
b100000110 P
1'
17
#950000
0'
07
#1000000
b1 N
b110 M
b10000011 J
b100110010 I
b10000011 5
b10000011 P
b1101011 K
b1101011 6
b1101011 Q
1'
17
#1050000
0'
07
#1100000
b10 N
b100110010 J
b111100001 I
b100110010 5
b100110010 P
1'
17
#1150000
0'
07
#1200000
b1 N
b101 M
b10011001 J
b101001000 I
b10011001 5
b10011001 P
b110101 K
b110101 6
b110101 Q
1'
17
#1250000
0'
07
#1300000
b10 N
b101001000 J
b111110111 I
b101001000 5
b101001000 P
1'
17
#1350000
0'
07
#1400000
b1 N
b100 M
b10100100 J
b101010011 I
b10100100 5
b10100100 P
b11010 K
b11010 6
b11010 Q
1'
17
#1450000
0'
07
#1500000
b10 N
1'
17
#1550000
0'
07
#1600000
b1 N
b11 M
b1010010 J
b100000001 I
b1010010 5
b1010010 P
b1101 K
b1101 6
b1101 Q
1'
17
#1650000
0'
07
#1700000
b10 N
b100000001 J
b110110000 I
b100000001 5
b100000001 P
1'
17
#1750000
0'
07
#1800000
b1 N
b10 M
b10000000 J
b100101111 I
b10000000 5
b10000000 P
b10000110 K
b10000110 6
b10000110 Q
1'
17
#1850000
0'
07
#1900000
b10 N
1'
17
#1950000
0'
07
#2000000
b1 N
b1 M
b1000000 J
b11101111 I
b1000000 5
b1000000 P
b1000011 K
b1000011 6
b1000011 Q
1'
17
#2050000
0'
07
#2100000
b10 N
b11101111 J
b110011110 I
b11101111 5
b11101111 P
1'
17
#2150000
0'
07
#2200000
b1 N
b0 M
b1110111 J
b100100110 I
b1110111 5
b1110111 P
b10100001 K
b10100001 6
b10100001 Q
1'
17
#2250000
0'
07
#2300000
0L
0:
1'
17
#2350000
0'
07
#2400000
b1110 E
1'
17
#2450000
0'
07
#2500000
b0 N
b1000 M
b1111000 I
b1 ;
b1 F
b1111 E
0D
1B
1T
0C
0H
1'
17
#2550000
0'
07
#2600000
b1110111 9
b1110111 R
b1 Y
1W
18
b10100001 V
b1110111 U
b101111000 S
b10001 E
1C
1H
1'
17
#2650000
0'
07
#2700000
b10 Y
b1000 X
b1 N
1L
1:
b10101111 K
b10101111 6
b10101111 Q
b0 J
b1 I
b0 5
b0 P
b10000 E
1'
17
#2750000
0'
07
#2800000
b11101111 9
b11101111 R
b1 Y
b11101111 U
b111110000 S
b1000010 V
b10 N
b1 J
b10 I
b1 5
b1 P
1'
17
#2850000
0'
07
#2900000
b10 Y
b111 X
b1 N
b111 M
b0 J
b1 I
b0 5
b0 P
b11010111 K
b11010111 6
b11010111 Q
1'
17
#2950000
0'
07
#3000000
b11011110 9
b11011110 R
b1 Y
b111011110 U
b11011111 S
b10000100 V
b10 N
b1 J
b10 I
b1 5
b1 P
1'
17
#3050000
0'
07
#3100000
b11011111 9
b11011111 R
b10 Y
b110 X
b11011111 U
b111100000 S
b1 N
b110 M
b0 J
b1 I
b0 5
b0 P
b11101011 K
b11101011 6
b11101011 Q
1'
17
#3150000
0'
07
#3200000
b10111111 9
b10111111 R
b1 Y
b110111111 U
b11000000 S
b1000 V
b10 N
b1 J
b10 I
b1 5
b1 P
1'
17
#3250000
0'
07
#3300000
b11000000 9
b11000000 R
b10 Y
b101 X
b11000000 U
b111000001 S
b1 N
b101 M
b0 J
b1 I
b0 5
b0 P
b11110101 K
b11110101 6
b11110101 Q
1'
17
#3350000
0'
07
#3400000
b10000000 9
b10000000 R
b1 Y
b110000000 U
b10000001 S
b10000 V
b10 N
b1 J
b10 I
b1 5
b1 P
1'
17
#3450000
0'
07
#3500000
b10000001 9
b10000001 R
b10 Y
b100 X
b10000001 U
b110000010 S
b1 N
b100 M
b0 J
b1 I
b0 5
b0 P
b11111010 K
b11111010 6
b11111010 Q
1'
17
#3550000
0'
07
#3600000
b10 9
b10 R
b1 Y
b100000010 U
b11 S
b100000 V
b10 N
1'
17
#3650000
0'
07
#3700000
b11 9
b11 R
b10 Y
b11 X
b11 U
b100000100 S
b1 N
b11 M
b1111101 K
b1111101 6
b1111101 Q
1'
17
#3750000
0'
07
#3800000
b110 9
b110 R
b1 Y
b110 U
b100000111 S
b1000000 V
b10 N
b1 J
b10 I
b1 5
b1 P
1'
17
#3850000
0'
07
#3900000
b10 Y
b10 X
b1 N
b10 M
b0 J
b1 I
b0 5
b0 P
b10111110 K
b10111110 6
b10111110 Q
1'
17
#3950000
0'
07
#4000000
b1100 9
b1100 R
b1 Y
b1100 U
b100001101 S
b10000000 V
b10 N
1'
17
#4050000
0'
07
#4100000
b10 Y
b1 X
b1 N
b1 M
b1011111 K
b1011111 6
b1011111 Q
1'
17
#4150000
0'
07
#4200000
b11001 9
b11001 R
b1 Y
b11001 U
b100011010 S
b0 V
b10 N
b1 J
b10 I
b1 5
b1 P
1'
17
#4250000
0'
07
#4300000
b10 Y
b0 X
b1 N
b0 M
b0 J
b1 I
b0 5
b0 P
b10101111 K
b10101111 6
b10101111 Q
1'
17
#4350000
0'
07
#4400000
0W
08
0L
0:
1'
17
#4450000
0'
07
#4500000
b10010 E
1'
17
#4550000
0'
07
#4600000
b0 Y
b1001 X
b0 N
b1000 M
b10011 E
b11001 ?
b11001 G
0B
0T
0C
0H
1'
17
#4650000
0'
07
#4700000
b10101 E
1B
1T
1'
17
#4750000
0'
07
#4800000
b0 9
b0 R
b1 Y
1W
18
b10101111 V
b0 U
b100000001 S
b10100 E
1'
17
#4850000
0'
07
#4900000
b10 Y
b1000 X
1'
17
#4950000
0'
07
#5000000
b1 9
b1 R
b1 Y
b1 U
b100000010 S
b1011110 V
1'
17
#5050000
0'
07
#5100000
b10 Y
b111 X
1'
17
#5150000
0'
07
#5200000
b10 9
b10 R
b1 Y
b10 U
b100000011 S
b10111100 V
1'
17
#5250000
0'
07
#5300000
b10 Y
b110 X
1'
17
#5350000
0'
07
#5400000
b101 9
b101 R
b1 Y
b101 U
b100000110 S
b1111000 V
1'
17
#5450000
0'
07
#5500000
b10 Y
b101 X
1'
17
#5550000
0'
07
#5600000
b1010 9
b1010 R
b1 Y
b1010 U
b100001011 S
b11110000 V
1'
17
#5650000
0'
07
#5700000
b10 Y
b100 X
1'
17
#5750000
0'
07
#5800000
b10101 9
b10101 R
b1 Y
b10101 U
b100010110 S
b11100000 V
1'
17
#5850000
0'
07
#5900000
b10 Y
b11 X
1'
17
#5950000
0'
07
#6000000
b101011 9
b101011 R
b1 Y
b101011 U
b100101100 S
b11000000 V
1'
17
#6050000
0'
07
#6100000
b10 Y
b10 X
1'
17
#6150000
0'
07
#6200000
b1010111 9
b1010111 R
b1 Y
b1010111 U
b101011000 S
b10000000 V
1'
17
#6250000
0'
07
#6300000
b10 Y
b1 X
1'
17
#6350000
0'
07
#6400000
b10101111 9
b10101111 R
b1 Y
b10101111 U
b110110000 S
b0 V
1'
17
#6450000
0'
07
#6500000
b10 Y
b0 X
1'
17
#6550000
0'
07
#6600000
0W
08
1'
17
#6650000
0'
07
#6700000
b10110 E
1'
17
#6750000
0'
07
#6800000
b0 Y
b1001 X
b10101111 I
b10101111 ;
b10101111 F
b11000 E
b10101111 @
b10101111 !
0B
0T
1'
17
#6850000
0'
07
#6900000
b10111 E
b1010111 =
1'
17
#6950000
0'
07
#7000000
b1 E
1'
17
#7050000
0'
07
#7100000
b1010 E
1'
17
#7150000
0'
07
#7200000
b11001 I
b11001 ;
b11001 F
b1011 E
1D
1'
17
#7250000
0'
07
#7300000
b1101 E
1C
1H
1'
17
#7350000
0'
07
#7400000
b1 N
1L
1:
b11001 K
b11001 6
b11001 Q
b1100 E
1'
17
#7450000
0'
07
#7500000
b10 N
b11001 J
b110010 I
b11001 5
b11001 P
1'
17
#7550000
0'
07
#7600000
b1 N
b111 M
b1100 J
b100101 I
b1100 5
b1100 P
b10001100 K
b10001100 6
b10001100 Q
1'
17
#7650000
0'
07
#7700000
b10 N
1'
17
#7750000
0'
07
#7800000
b1 N
b110 M
b110 J
b11111 I
b110 5
b110 P
b1000110 K
b1000110 6
b1000110 Q
1'
17
#7850000
0'
07
#7900000
b10 N
1'
17
#7950000
0'
07
#8000000
b1 N
b101 M
b11 J
b11100 I
b11 5
b11 P
b100011 K
b100011 6
b100011 Q
1'
17
#8050000
0'
07
#8100000
b10 N
b11100 J
b110101 I
b11100 5
b11100 P
1'
17
#8150000
0'
07
#8200000
b1 N
b100 M
b1110 J
b100111 I
b1110 5
b1110 P
b10001 K
b10001 6
b10001 Q
1'
17
#8250000
0'
07
#8300000
b10 N
b100111 J
b1000000 I
b100111 5
b100111 P
1'
17
#8350000
0'
07
#8400000
b1 N
b11 M
b10011 J
b101100 I
b10011 5
b10011 P
b10001000 K
b10001000 6
b10001000 Q
1'
17
#8450000
0'
07
#8500000
b10 N
1'
17
#8550000
0'
07
#8600000
b1 N
b10 M
b1001 J
b100010 I
b1001 5
b1001 P
b11000100 K
b11000100 6
b11000100 Q
1'
17
#8650000
0'
07
#8700000
b10 N
1'
17
#8750000
0'
07
#8800000
b1 N
b1 M
b100 J
b11101 I
b100 5
b100 P
b11100010 K
b11100010 6
b11100010 Q
1'
17
#8850000
0'
07
#8900000
b10 N
1'
17
#8950000
0'
07
#9000000
b1 N
b0 M
b10 J
b11011 I
b10 5
b10 P
b1110001 K
b1110001 6
b1110001 Q
1'
17
#9050000
0'
07
#9100000
0L
0:
1'
17
#9150000
0'
07
#9200000
b1110 E
1'
17
#9250000
0'
07
#9300000
b0 N
b1000 M
b10110001 I
b10101111 ;
b10101111 F
b1111 E
0D
1B
1T
0C
0H
1'
17
#9350000
0'
07
#9400000
b10 9
b10 R
b1 Y
1W
18
b1110001 V
b10 U
b100000011 S
b10001 E
1C
1H
1'
17
#9450000
0'
07
#9500000
b10 Y
b1000 X
b1 N
1L
1:
b11001 K
b11001 6
b11001 Q
b0 J
b10101111 I
b0 5
b0 P
b10000 E
1'
17
#9550000
0'
07
#9600000
b100 9
b100 R
b1 Y
b100 U
b100000101 S
b11100010 V
b10 N
b10101111 J
b101011110 I
b10101111 5
b10101111 P
1'
17
#9650000
0'
07
#9700000
b10 Y
b111 X
b1 N
b111 M
b1010111 J
b100000110 I
b1010111 5
b1010111 P
b10001100 K
b10001100 6
b10001100 Q
1'
17
#9750000
0'
07
#9800000
b1001 9
b1001 R
b1 Y
b1001 U
b100001010 S
b11000100 V
b10 N
1'
17
#9850000
0'
07
#9900000
b10 Y
b110 X
b1 N
b110 M
b101011 J
b11011010 I
b101011 5
b101011 P
b11000110 K
b11000110 6
b11000110 Q
1'
17
#9950000
0'
07
#10000000
b10011 9
b10011 R
b1 Y
b10011 U
b100010100 S
b10001000 V
b10 N
1'
17
#10050000
0'
07
#10100000
b10 Y
b101 X
b1 N
b101 M
b10101 J
b11000100 I
b10101 5
b10101 P
b11100011 K
b11100011 6
b11100011 Q
1'
17
#10150000
0'
07
#10200000
b100111 9
b100111 R
b1 Y
b100111 U
b100101000 S
b10000 V
b10 N
b11000100 J
b101110011 I
b11000100 5
b11000100 P
1'
17
#10250000
0'
07
#10300000
b10 Y
b100 X
b1 N
b100 M
b1100010 J
b100010001 I
b1100010 5
b1100010 P
b1110001 K
b1110001 6
b1110001 Q
1'
17
#10350000
0'
07
#10400000
b1001110 9
b1001110 R
b1 Y
b1001110 U
b101001111 S
b100000 V
b10 N
b100010001 J
b111000000 I
b100010001 5
b100010001 P
1'
17
#10450000
0'
07
#10500000
b10 Y
b11 X
b1 N
b11 M
b10001000 J
b100110111 I
b10001000 5
b10001000 P
b10111000 K
b10111000 6
b10111000 Q
1'
17
#10550000
0'
07
#10600000
b10011100 9
b10011100 R
b1 Y
b10011100 U
b110011101 S
b1000000 V
b10 N
1'
17
#10650000
0'
07
#10700000
b10 Y
b10 X
b1 N
b10 M
b1000100 J
b11110011 I
b1000100 5
b1000100 P
b1011100 K
b1011100 6
b1011100 Q
1'
17
#10750000
0'
07
#10800000
b111000 9
b111000 R
b1 Y
b100111000 U
b111001 S
b10000000 V
b10 N
1'
17
#10850000
0'
07
#10900000
b111001 9
b111001 R
b10 Y
b1 X
b111001 U
b100111010 S
b1 N
b1 M
b100010 J
b11010001 I
b100010 5
b100010 P
b101110 K
b101110 6
b101110 Q
1'
17
#10950000
0'
07
#11000000
b1110011 9
b1110011 R
b1 Y
b1110011 U
b101110100 S
b0 V
b10 N
1'
17
#11050000
0'
07
#11100000
b10 Y
b0 X
b1 N
b0 M
b10001 J
b11000000 I
b10001 5
b10001 P
b10111 K
b10111 6
b10111 Q
1'
17
#11150000
0'
07
#11200000
0W
08
0L
0:
1'
17
#11250000
0'
07
#11300000
b10010 E
1'
17
#11350000
0'
07
#11400000
b0 Y
b1001 X
b0 N
b1000 M
b10011 E
b1110011 ?
b1110011 G
0B
0T
0C
0H
1'
17
#11450000
0'
07
#11500000
b10101 E
1B
1T
1'
17
#11550000
0'
07
#11600000
b10001 9
b10001 R
b1 Y
1W
18
b10111 V
b10001 U
b100010010 S
b10100 E
1'
17
#11650000
0'
07
#11700000
b10 Y
b1000 X
1'
17
#11750000
0'
07
#11800000
b100010 9
b100010 R
b1 Y
b100010 U
b100100011 S
b101110 V
1'
17
#11850000
0'
07
#11900000
b10 Y
b111 X
1'
17
#11950000
0'
07
#12000000
b1000100 9
b1000100 R
b1 Y
b1000100 U
b101000101 S
b1011100 V
1'
17
#12050000
0'
07
#12100000
b10 Y
b110 X
1'
17
#12150000
0'
07
#12200000
b10001000 9
b10001000 R
b1 Y
b10001000 U
b110001001 S
b10111000 V
1'
17
#12250000
0'
07
#12300000
b10 Y
b101 X
1'
17
#12350000
0'
07
#12400000
b10001 9
b10001 R
b1 Y
b100010001 U
b10010 S
b1110000 V
1'
17
#12450000
0'
07
#12500000
b10010 9
b10010 R
b10 Y
b100 X
b10010 U
b100010011 S
1'
17
#12550000
0'
07
#12600000
b100100 9
b100100 R
b1 Y
b100100 U
b100100101 S
b11100000 V
1'
17
#12650000
0'
07
#12700000
b10 Y
b11 X
1'
17
#12750000
0'
07
#12800000
b1001001 9
b1001001 R
b1 Y
b1001001 U
b101001010 S
b11000000 V
1'
17
#12850000
0'
07
#12900000
b10 Y
b10 X
1'
17
#12950000
0'
07
#13000000
b10010011 9
b10010011 R
b1 Y
b10010011 U
b110010100 S
b10000000 V
1'
17
#13050000
0'
07
#13100000
b10 Y
b1 X
1'
17
#13150000
0'
07
#13200000
b100111 9
b100111 R
b1 Y
b100100111 U
b101000 S
b0 V
1'
17
#13250000
0'
07
#13300000
b101000 9
b101000 R
b10 Y
b0 X
b101000 U
b100101001 S
1'
17
#13350000
0'
07
#13400000
0W
08
1'
17
#13450000
0'
07
#13500000
b10110 E
1'
17
#13550000
0'
07
#13600000
b0 Y
b1001 X
b111001 I
b101000 ;
b101000 F
b11000 E
b101000 @
b101000 !
0B
0T
1'
17
#13650000
0'
07
#13700000
b10111 E
b101011 =
1'
17
#13750000
0'
07
#13800000
b1 E
1'
17
#13850000
0'
07
#13900000
b1010 E
1'
17
#13950000
0'
07
#14000000
b10000100 I
b1110011 ;
b1110011 F
b1011 E
1D
1'
17
#14050000
0'
07
#14100000
b1101 E
1C
1H
1'
17
#14150000
0'
07
#14200000
b1 N
1L
1:
b1110011 K
b1110011 6
b1110011 Q
b0 J
b1110011 I
b0 5
b0 P
b1100 E
1'
17
#14250000
0'
07
#14300000
b10 N
b1110011 J
b11100110 I
b1110011 5
b1110011 P
1'
17
#14350000
0'
07
#14400000
b1 N
b111 M
b111001 J
b10101100 I
b111001 5
b111001 P
b10111001 K
b10111001 6
b10111001 Q
1'
17
#14450000
0'
07
